[
  {
    "id": "1153714",
    "type": "movie",
    "title": "Death of a Unicorn",
    "content": "Odd 6 NOW PLAYING",
    "backdrop": "https://media.themoviedb.org/t/p/w1920_and_h427_multi_faces/foJq553dbhQ5KG1vSzd6rnwSAHO.jpg",
    "trailerId": "uG2gsnq7SJE",
    "trailerUrl": "https://www.youtube.com/embed/uG2gsnq7SJE",
    "poster_image": "https://media.themoviedb.org/t/p/w355_and_h200_multi_faces/18iGjkavP8KLfyU3Ifkp9s2bSvD.jpg"
  },
  {
    "id": "986056",
    "type": "movie",
    "title": "Thunderbolts*",
    "content": "In Theaters May 2",
    "backdrop": "https://media.themoviedb.org/t/p/w1920_and_h427_multi_faces/qTfbBxJnTX6G3p9dGsgi6HFNCFZ.jpg",
    "trailerId": "RwgqnSkUDqc",
    "trailerUrl": "https://www.youtube.com/embed/RwgqnSkUDqc",
    "poster_image": "https://media.themoviedb.org/t/p/w355_and_h200_multi_faces/18iGjkavP8KLfyU3Ifkp9s2bSvD.jpg"
  },
  {
    "id": "1233413",
    "type": "movie",
    "title": "Sinners",
    "content": "There will be signs.",
    "backdrop": "https://media.themoviedb.org/t/p/w1920_and_h427_multi_faces/lwfbwY5QjUtM3slQoGZUPhuS0eD.jpg",
    "trailerId": "wq1HRpz5KUE",
    "trailerUrl": "https://www.youtube.com/embed/wq1HRpz5KUE",
    "poster_image": "https://media.themoviedb.org/t/p/w355_and_h200_multi_faces/18iGjkavP8KLfyU3Ifkp9s2bSvD.jpg"
  },
  {
    "id": "950387",
    "type": "movie",
    "title": "A Minecraft Movie",
    "content": "Any questions?",
    "backdrop": "https://media.themoviedb.org/t/p/w1920_and_h427_multi_faces/2Nti3gYAX513wvhp8IiLL6ZDyOm.jpg",
    "trailerId": "qvryjVRbT1E",
    "trailerUrl": "https://www.youtube.com/embed/qvryjVRbT1E",
    "poster_image": "https://media.themoviedb.org/t/p/w355_and_h200_multi_faces/18iGjkavP8KLfyU3Ifkp9s2bSvD.jpg"
  },
  {
    "id": "762509",
    "type": "movie",
    "title": "Mufasa: The Lion King",
    "content": "\"Feel It\"",
    "backdrop": "https://media.themoviedb.org/t/p/w1920_and_h427_multi_faces/1w8kutrRucTd3wlYyu5QlUDMiG1.jpg",
    "trailerId": "dfLM5lka_5Q",
    "trailerUrl": "https://www.youtube.com/embed/dfLM5lka_5Q",
    "poster_image": "https://media.themoviedb.org/t/p/w355_and_h200_multi_faces/18iGjkavP8KLfyU3Ifkp9s2bSvD.jpg"
  },
  {
    "id": "1054867",
    "type": "movie",
    "title": "One Battle After Another",
    "content": "Official Trailer Online Now",
    "backdrop": "https://media.themoviedb.org/t/p/w1920_and_h427_multi_faces/ev06XwWLSoTG2DkLlsllAhlWGsk.jpg",
    "trailerId": "XETfXtXGP5k",
    "trailerUrl": "https://www.youtube.com/embed/XETfXtXGP5k",
    "poster_image": "https://media.themoviedb.org/t/p/w355_and_h200_multi_faces/18iGjkavP8KLfyU3Ifkp9s2bSvD.jpg"
  },
  {
    "id": "1087891",
    "type": "movie",
    "title": "The Amateur",
    "content": "Only In Theaters April 11",
    "backdrop": "https://media.themoviedb.org/t/p/w1920_and_h427_multi_faces/8vVbNSjfcgpYh8lOQbEr8MBSkIu.jpg",
    "trailerId": "115ADeUZ9lc",
    "trailerUrl": "https://www.youtube.com/embed/115ADeUZ9lc",
    "poster_image": "https://media.themoviedb.org/t/p/w355_and_h200_multi_faces/18iGjkavP8KLfyU3Ifkp9s2bSvD.jpg"
  },
  {
    "id": "447273",
    "type": "movie",
    "title": "Snow White",
    "content": "The merry tunes of Snow White",
    "backdrop": "https://media.themoviedb.org/t/p/w1920_and_h427_multi_faces/2siOHQYDG7gCQB6g69g2pTZiSia.jpg",
    "trailerId": "L6DJwlEWWVw",
    "trailerUrl": "https://www.youtube.com/embed/L6DJwlEWWVw",
    "poster_image": "https://media.themoviedb.org/t/p/w355_and_h200_multi_faces/18iGjkavP8KLfyU3Ifkp9s2bSvD.jpg"
  },
  {
    "id": "574475",
    "type": "movie",
    "title": "Final Destination Bloodlines",
    "content": "Trailer Out Now",
    "backdrop": "https://media.themoviedb.org/t/p/w1920_and_h427_multi_faces/bse2E5xgKcsL6w8h2efqpecvnxV.jpg",
    "trailerId": "HlMRjIPvzQ8",
    "trailerUrl": "https://www.youtube.com/embed/HlMRjIPvzQ8",
    "poster_image": "https://media.themoviedb.org/t/p/w355_and_h200_multi_faces/18iGjkavP8KLfyU3Ifkp9s2bSvD.jpg"
  },
  {
    "id": "1241982",
    "type": "movie",
    "title": "Moana 2",
    "content": "Pua\u2019s best moments? Say less.",
    "backdrop": "https://media.themoviedb.org/t/p/w1920_and_h427_multi_faces/zo8CIjJ2nfNOevqNajwMRO6Hwka.jpg",
    "trailerId": "-F-8OxgYOkE",
    "trailerUrl": "https://www.youtube.com/embed/-F-8OxgYOkE",
    "poster_image": "https://media.themoviedb.org/t/p/w355_and_h200_multi_faces/18iGjkavP8KLfyU3Ifkp9s2bSvD.jpg"
  },
  {
    "id": "202555",
    "type": "tv",
    "title": "Daredevil: Born Again",
    "content": "Alive",
    "backdrop": "https://media.themoviedb.org/t/p/w1920_and_h427_multi_faces/7bNw4yfFQOWXZKKMFxFWIbFmsys.jpg",
    "trailerId": "_5yR6UZjkyY",
    "trailerUrl": "https://www.youtube.com/embed/_5yR6UZjkyY",
    "poster_image": "https://media.themoviedb.org/t/p/w355_and_h200_multi_faces/18iGjkavP8KLfyU3Ifkp9s2bSvD.jpg"
  },
  {
    "id": "1075456",
    "type": "movie",
    "title": "O'Dessa",
    "content": "Facejob",
    "backdrop": "https://media.themoviedb.org/t/p/w1920_and_h427_multi_faces/7z2lSLmiJ5jNeYCoXmton86BapN.jpg",
    "trailerId": "6yM_YM2IXAs",
    "trailerUrl": "https://www.youtube.com/embed/6yM_YM2IXAs",
    "poster_image": "https://media.themoviedb.org/t/p/w355_and_h200_multi_faces/18iGjkavP8KLfyU3Ifkp9s2bSvD.jpg"
  },
  {
    "id": "1249213",
    "type": "movie",
    "title": "Drop",
    "content": "Official Trailer 2",
    "backdrop": "https://media.themoviedb.org/t/p/w1920_and_h427_multi_faces/pg8DVHZCUhwdrSX6Pb0Ut4ST6GM.jpg",
    "trailerId": "tZoNPCc-2Vw",
    "trailerUrl": "https://www.youtube.com/embed/tZoNPCc-2Vw",
    "poster_image": "https://media.themoviedb.org/t/p/w355_and_h200_multi_faces/18iGjkavP8KLfyU3Ifkp9s2bSvD.jpg"
  },
  {
    "id": "1244944",
    "type": "movie",
    "title": "The Woman in the Yard",
    "content": "Only In Theaters Now",
    "backdrop": "https://media.themoviedb.org/t/p/w1920_and_h427_multi_faces/mBiEavD7rADFZrECO7hzGi6hVMu.jpg",
    "trailerId": "lp1x0e-3Hkg",
    "trailerUrl": "https://www.youtube.com/embed/lp1x0e-3Hkg",
    "poster_image": "https://media.themoviedb.org/t/p/w355_and_h200_multi_faces/18iGjkavP8KLfyU3Ifkp9s2bSvD.jpg"
  },
  {
    "id": "1197306",
    "type": "movie",
    "title": "A Working Man",
    "content": "Final Trailer",
    "backdrop": "https://media.themoviedb.org/t/p/w1920_and_h427_multi_faces/fTrQsdMS2MUw00RnzH0r3JWHhts.jpg",
    "trailerId": "mdfrG2cLK58",
    "trailerUrl": "https://www.youtube.com/embed/mdfrG2cLK58",
    "poster_image": "https://media.themoviedb.org/t/p/w355_and_h200_multi_faces/18iGjkavP8KLfyU3Ifkp9s2bSvD.jpg"
  },
  {
    "id": "82782",
    "type": "tv",
    "title": "The Righteous Gemstones",
    "content": "Season 4 Episode 4 Preview",
    "backdrop": "https://media.themoviedb.org/t/p/w1920_and_h427_multi_faces/vXPxMNfuapkRXBUhac3LAkuzSzc.jpg",
    "trailerId": "rA1Q8LICB8s",
    "trailerUrl": "https://www.youtube.com/embed/rA1Q8LICB8s",
    "poster_image": "https://media.themoviedb.org/t/p/w355_and_h200_multi_faces/18iGjkavP8KLfyU3Ifkp9s2bSvD.jpg"
  },
  {
    "id": "219246",
    "type": "tv",
    "title": "When Life Gives You Tangerines",
    "content": "Volume 4 Trailer [ENG SUB]",
    "backdrop": "https://media.themoviedb.org/t/p/w1920_and_h427_multi_faces/mwczMJeoQrsPERcyP1e900jo3Jv.jpg",
    "trailerId": "suxklHratKI",
    "trailerUrl": "https://www.youtube.com/embed/suxklHratKI",
    "poster_image": "https://media.themoviedb.org/t/p/w355_and_h200_multi_faces/18iGjkavP8KLfyU3Ifkp9s2bSvD.jpg"
  },
  {
    "id": "127532",
    "type": "tv",
    "title": "Solo Leveling",
    "content": "Season 2 -Arise from the Shadow- HYPE TRAILER",
    "backdrop": "https://media.themoviedb.org/t/p/w1920_and_h427_multi_faces/odVlTMqPPiMksmxpN9cCbPCjUPP.jpg",
    "trailerId": "IDQjoTkgSK8",
    "trailerUrl": "https://www.youtube.com/embed/IDQjoTkgSK8",
    "poster_image": "https://media.themoviedb.org/t/p/w355_and_h200_multi_faces/18iGjkavP8KLfyU3Ifkp9s2bSvD.jpg"
  },
  {
    "id": "207332",
    "type": "tv",
    "title": "SAKAMOTO DAYS",
    "content": "Part 1 Now Playing on Netflix",
    "backdrop": "https://media.themoviedb.org/t/p/w1920_and_h427_multi_faces/blSthAPRbEOJBowdxppeQqNPRh9.jpg",
    "trailerId": "gLBCpN0evko",
    "trailerUrl": "https://www.youtube.com/embed/gLBCpN0evko",
    "poster_image": "https://media.themoviedb.org/t/p/w355_and_h200_multi_faces/18iGjkavP8KLfyU3Ifkp9s2bSvD.jpg"
  },
  {
    "id": "1013601",
    "type": "movie",
    "title": "The Alto Knights",
    "content": "Get your tickets now, capeesh?",
    "backdrop": "https://media.themoviedb.org/t/p/w1920_and_h427_multi_faces/mY6wA686iFOhhhBX1GyA8Et1dyl.jpg",
    "trailerId": "kyd0ZbMF1Bo",
    "trailerUrl": "https://www.youtube.com/embed/kyd0ZbMF1Bo",
    "poster_image": "https://media.themoviedb.org/t/p/w355_and_h200_multi_faces/18iGjkavP8KLfyU3Ifkp9s2bSvD.jpg"
  },
  {
    "id": "10135",
    "type": "movie",
    "title": "Road House",
    "content": "Original Trailer",
    "backdrop": "https://media.themoviedb.org/t/p/w1920_and_h427_multi_faces/fBORcwQlM9zCD5iqHxEl8VmxElu.jpg",
    "trailerId": "xbN9m-1vIZc",
    "trailerUrl": "https://www.youtube.com/embed/xbN9m-1vIZc",
    "poster_image": "https://media.themoviedb.org/t/p/w355_and_h200_multi_faces/18iGjkavP8KLfyU3Ifkp9s2bSvD.jpg"
  },
  {
    "id": "78191",
    "type": "tv",
    "title": "You",
    "content": "YOU | Series Trailer | Netflix",
    "backdrop": "https://media.themoviedb.org/t/p/w1920_and_h427_multi_faces/gzOIymABxmetAECXtazEYCpMmfb.jpg",
    "trailerId": "v99ooSjCVhg",
    "trailerUrl": "https://www.youtube.com/embed/v99ooSjCVhg",
    "poster_image": "https://media.themoviedb.org/t/p/w355_and_h200_multi_faces/18iGjkavP8KLfyU3Ifkp9s2bSvD.jpg"
  },
  {
    "id": "207411",
    "type": "tv",
    "title": "Good American Family",
    "content": "\"A Transfixing Watch\"",
    "backdrop": "https://media.themoviedb.org/t/p/w1920_and_h427_multi_faces/jkyjkLuKxKa2PXaTcPDfrBUHxi8.jpg",
    "trailerId": "Xr8X3cdb3lk",
    "trailerUrl": "https://www.youtube.com/embed/Xr8X3cdb3lk",
    "poster_image": "https://media.themoviedb.org/t/p/w355_and_h200_multi_faces/18iGjkavP8KLfyU3Ifkp9s2bSvD.jpg"
  },
  {
    "id": "114500",
    "type": "tv",
    "title": "Win or Lose",
    "content": "Van-extra",
    "backdrop": "https://media.themoviedb.org/t/p/w1920_and_h427_multi_faces/erJMfbBfhasNw6gKpp8D1llxmPu.jpg",
    "trailerId": "FwmP3um99SI",
    "trailerUrl": "https://www.youtube.com/embed/FwmP3um99SI",
    "poster_image": "https://media.themoviedb.org/t/p/w355_and_h200_multi_faces/18iGjkavP8KLfyU3Ifkp9s2bSvD.jpg"
  },
  {
    "id": "37854",
    "type": "tv",
    "title": "One Piece",
    "content": "Egghead Island Part 2 Official Trailer [Subtitled]",
    "backdrop": "https://media.themoviedb.org/t/p/w1920_and_h427_multi_faces/4Mt7WHox67uJ1yErwTBFcV8KWgG.jpg",
    "trailerId": "3NUizzImhig",
    "trailerUrl": "https://www.youtube.com/embed/3NUizzImhig",
    "poster_image": "https://media.themoviedb.org/t/p/w355_and_h200_multi_faces/18iGjkavP8KLfyU3Ifkp9s2bSvD.jpg"
  },
  {
    "id": "10086",
    "type": "movie",
    "title": "Man Bites Dog",
    "content": "Original Trailer [Subtitled]",
    "backdrop": "https://media.themoviedb.org/t/p/w1920_and_h427_multi_faces/7QLGk7qKm66dtjTtpVeAIRocoan.jpg",
    "trailerId": "3HFuTY3HpV8",
    "trailerUrl": "https://www.youtube.com/embed/3HFuTY3HpV8",
    "poster_image": "https://media.themoviedb.org/t/p/w355_and_h200_multi_faces/18iGjkavP8KLfyU3Ifkp9s2bSvD.jpg"
  },
  {
    "id": "4482",
    "type": "tv",
    "title": "Bewitched",
    "content": "Seasons 3 & 4 | Limited Edition Blu-ray Trailer",
    "backdrop": "https://media.themoviedb.org/t/p/w1920_and_h427_multi_faces/yMYSrL0YI5hgDnBlEBRlKRI1Hsw.jpg",
    "trailerId": "CyFUZI4228s",
    "trailerUrl": "https://www.youtube.com/embed/CyFUZI4228s",
    "poster_image": "https://media.themoviedb.org/t/p/w355_and_h200_multi_faces/18iGjkavP8KLfyU3Ifkp9s2bSvD.jpg"
  },
  {
    "id": "69478",
    "type": "tv",
    "title": "The Handmaid's Tale",
    "content": "Final Season Trailer",
    "backdrop": "https://media.themoviedb.org/t/p/w1920_and_h427_multi_faces/sokTOq0zAmPS7wCR4qd4Kca35x7.jpg",
    "trailerId": "xBBRUdLBsFI",
    "trailerUrl": "https://www.youtube.com/embed/xBBRUdLBsFI",
    "poster_image": "https://media.themoviedb.org/t/p/w355_and_h200_multi_faces/18iGjkavP8KLfyU3Ifkp9s2bSvD.jpg"
  },
  {
    "id": "1189735",
    "type": "movie",
    "title": "Fr\u00e9waka",
    "content": "Official Trailer [Subtitled]",
    "backdrop": "https://media.themoviedb.org/t/p/w1920_and_h427_multi_faces/qj0GN10AC65FcJchKLTDmOFE15X.jpg",
    "trailerId": "-FjzW6eFIsk",
    "trailerUrl": "https://www.youtube.com/embed/-FjzW6eFIsk",
    "poster_image": "https://media.themoviedb.org/t/p/w355_and_h200_multi_faces/18iGjkavP8KLfyU3Ifkp9s2bSvD.jpg"
  },
  {
    "id": "100088",
    "type": "tv",
    "title": "The Last of Us",
    "content": "Endure and survive.",
    "backdrop": "https://media.themoviedb.org/t/p/w1920_and_h427_multi_faces/lY2DhbA7Hy44fAKddr06UrXWWaQ.jpg",
    "trailerId": "65mPHv6vNQc",
    "trailerUrl": "https://www.youtube.com/embed/65mPHv6vNQc",
    "poster_image": "https://media.themoviedb.org/t/p/w355_and_h200_multi_faces/18iGjkavP8KLfyU3Ifkp9s2bSvD.jpg"
  },
  {
    "id": "65334",
    "type": "tv",
    "title": "Miraculous: Tales of Ladybug & Cat Noir",
    "content": "Teaser",
    "backdrop": "https://media.themoviedb.org/t/p/w1920_and_h427_multi_faces/h8Lxf8gCI6uQqmnoWfQxjaJgrul.jpg",
    "trailerId": "AHpi1JmG274",
    "trailerUrl": "https://www.youtube.com/embed/AHpi1JmG274",
    "poster_image": "https://media.themoviedb.org/t/p/w355_and_h200_multi_faces/18iGjkavP8KLfyU3Ifkp9s2bSvD.jpg"
  },
  {
    "id": "17937",
    "type": "tv",
    "title": "Ghost Adventures",
    "content": "Sneak Peak: New Season",
    "backdrop": "https://media.themoviedb.org/t/p/w1920_and_h427_multi_faces/u64huzTnF3jEYUXJ4BDlpHy2L3K.jpg",
    "trailerId": "bpL08l_WwDI",
    "trailerUrl": "https://www.youtube.com/embed/bpL08l_WwDI",
    "poster_image": "https://media.themoviedb.org/t/p/w355_and_h200_multi_faces/18iGjkavP8KLfyU3Ifkp9s2bSvD.jpg"
  },
  {
    "id": "245079",
    "type": "tv",
    "title": "Hyper Knife",
    "content": "Official Trailer [Subtitled]",
    "backdrop": "https://media.themoviedb.org/t/p/w1920_and_h427_multi_faces/1dxBi0VlYly8xqVquXWNeiPSClP.jpg",
    "trailerId": "JY73T7jgex8",
    "trailerUrl": "https://www.youtube.com/embed/JY73T7jgex8",
    "poster_image": "https://media.themoviedb.org/t/p/w355_and_h200_multi_faces/18iGjkavP8KLfyU3Ifkp9s2bSvD.jpg"
  },
  {
    "id": "210213",
    "type": "tv",
    "title": "Gannibal",
    "content": "Season 2 Official Trailer [Subtitled]",
    "backdrop": "https://media.themoviedb.org/t/p/w1920_and_h427_multi_faces/oilobjVpXlSaDDj67raoNqdHrfB.jpg",
    "trailerId": "TvN19xMrVwc",
    "trailerUrl": "https://www.youtube.com/embed/TvN19xMrVwc",
    "poster_image": "https://media.themoviedb.org/t/p/w355_and_h200_multi_faces/18iGjkavP8KLfyU3Ifkp9s2bSvD.jpg"
  },
  {
    "id": "42009",
    "type": "tv",
    "title": "Black Mirror",
    "content": "Season 7 Official Trailer",
    "backdrop": "https://media.themoviedb.org/t/p/w1920_and_h427_multi_faces/38aCLy0BdFbOAIEfuDladoITHN0.jpg",
    "trailerId": "1iqra1ojEvM",
    "trailerUrl": "https://www.youtube.com/embed/1iqra1ojEvM",
    "poster_image": "https://media.themoviedb.org/t/p/w355_and_h200_multi_faces/18iGjkavP8KLfyU3Ifkp9s2bSvD.jpg"
  },
  {
    "id": "158439",
    "type": "tv",
    "title": "Marie Antoinette",
    "content": "Marie-Antoinette (Season 2) | Trailer",
    "backdrop": "https://media.themoviedb.org/t/p/w1920_and_h427_multi_faces/fDb7cQEchbFrz9obz891xD1P65z.jpg",
    "trailerId": "YJnCBcD9nmc",
    "trailerUrl": "https://www.youtube.com/embed/YJnCBcD9nmc",
    "poster_image": "https://media.themoviedb.org/t/p/w355_and_h200_multi_faces/18iGjkavP8KLfyU3Ifkp9s2bSvD.jpg"
  },
  {
    "id": "237512",
    "type": "tv",
    "title": "Jurassic World: Chaos Theory",
    "content": "Season 3 Official Trailer",
    "backdrop": "https://media.themoviedb.org/t/p/w1920_and_h427_multi_faces/7y31JWag4vsWtXZvcjmLUDJ6NSp.jpg",
    "trailerId": "5gpNHQPCR24",
    "trailerUrl": "https://www.youtube.com/embed/5gpNHQPCR24",
    "poster_image": "https://media.themoviedb.org/t/p/w355_and_h200_multi_faces/18iGjkavP8KLfyU3Ifkp9s2bSvD.jpg"
  },
  {
    "id": "50712",
    "type": "tv",
    "title": "Black Butler",
    "content": "Emerald Witch Arc Official Trailer 2 [Subtitled]",
    "backdrop": "https://media.themoviedb.org/t/p/w1920_and_h427_multi_faces/5U0dYTkHXPhoExNnEm5iKrpDqtr.jpg",
    "trailerId": "ue_GjpV8nrc",
    "trailerUrl": "https://www.youtube.com/embed/ue_GjpV8nrc",
    "poster_image": "https://media.themoviedb.org/t/p/w355_and_h200_multi_faces/18iGjkavP8KLfyU3Ifkp9s2bSvD.jpg"
  },
  {
    "id": "124101",
    "type": "tv",
    "title": "Hacks",
    "content": "Season 4 Official Trailer",
    "backdrop": "https://media.themoviedb.org/t/p/w1920_and_h427_multi_faces/qeqJI8LRIdbV2kZT3rtOaHOnLuY.jpg",
    "trailerId": "hOwKjb_EHJA",
    "trailerUrl": "https://www.youtube.com/embed/hOwKjb_EHJA",
    "poster_image": "https://media.themoviedb.org/t/p/w355_and_h200_multi_faces/18iGjkavP8KLfyU3Ifkp9s2bSvD.jpg"
  },
  {
    "id": "128904",
    "type": "tv",
    "title": "Dark Winds",
    "content": "\"A Miracle in the Current Era of Television\"",
    "backdrop": "https://media.themoviedb.org/t/p/w1920_and_h427_multi_faces/aLC4Uh8v2VRmT1cRfNspFHp6OFj.jpg",
    "trailerId": "cCRK1YXGzTU",
    "trailerUrl": "https://www.youtube.com/embed/cCRK1YXGzTU",
    "poster_image": "https://media.themoviedb.org/t/p/w355_and_h200_multi_faces/18iGjkavP8KLfyU3Ifkp9s2bSvD.jpg"
  },
  {
    "id": "247767",
    "type": "tv",
    "title": "The Studio",
    "content": "Official Trailer",
    "backdrop": "https://media.themoviedb.org/t/p/w1920_and_h427_multi_faces/aSOrTfmIL211gjenXoRzvBoxgYv.jpg",
    "trailerId": "EIQuE7JGXU8",
    "trailerUrl": "https://www.youtube.com/embed/EIQuE7JGXU8",
    "poster_image": "https://media.themoviedb.org/t/p/w355_and_h200_multi_faces/18iGjkavP8KLfyU3Ifkp9s2bSvD.jpg"
  },
  {
    "id": "223500",
    "type": "tv",
    "title": "WIND BREAKER",
    "content": "Season 2 Main Trailer [Subtitled]",
    "backdrop": "https://media.themoviedb.org/t/p/w1920_and_h427_multi_faces/czrAvoN103RYYX8lhkZPs2zgnkl.jpg",
    "trailerId": "ITwTpnS56TA",
    "trailerUrl": "https://www.youtube.com/embed/ITwTpnS56TA",
    "poster_image": "https://media.themoviedb.org/t/p/w355_and_h200_multi_faces/18iGjkavP8KLfyU3Ifkp9s2bSvD.jpg"
  },
  {
    "id": "243217",
    "type": "tv",
    "title": "Happy Face",
    "content": "Official Trailer",
    "backdrop": "https://media.themoviedb.org/t/p/w1920_and_h427_multi_faces/jpo9nZOayoh7IHIIXa6jRT6WP9L.jpg",
    "trailerId": "1e2bUS9ROrw",
    "trailerUrl": "https://www.youtube.com/embed/1e2bUS9ROrw",
    "poster_image": "https://media.themoviedb.org/t/p/w355_and_h200_multi_faces/18iGjkavP8KLfyU3Ifkp9s2bSvD.jpg"
  },
  {
    "id": "271309",
    "type": "tv",
    "title": "Buried Hearts",
    "content": "Episode 3 Trailer | Buried Hearts | Disney+ Hotstar Indonesia",
    "backdrop": "https://media.themoviedb.org/t/p/w1920_and_h427_multi_faces/vJMoMgjavkgkaUBDGQVVv4OjTjf.jpg",
    "trailerId": "ymcLW9sFE8U",
    "trailerUrl": "https://www.youtube.com/embed/ymcLW9sFE8U",
    "poster_image": "https://media.themoviedb.org/t/p/w355_and_h200_multi_faces/18iGjkavP8KLfyU3Ifkp9s2bSvD.jpg"
  },
  {
    "id": "2666",
    "type": "movie",
    "title": "Dark City",
    "content": "Original Trailer",
    "backdrop": "https://media.themoviedb.org/t/p/w1920_and_h427_multi_faces/cS992RPEJQ4S45IiNSLqlMl2ins.jpg",
    "trailerId": "30mmoegSQCs",
    "trailerUrl": "https://www.youtube.com/embed/30mmoegSQCs",
    "poster_image": "https://media.themoviedb.org/t/p/w355_and_h200_multi_faces/18iGjkavP8KLfyU3Ifkp9s2bSvD.jpg"
  },
  {
    "id": "9705",
    "type": "movie",
    "title": "Swordfish",
    "content": "Original Trailer",
    "backdrop": "https://media.themoviedb.org/t/p/w1920_and_h427_multi_faces/eSxvC0Qw0A9AfI355MF9dSItrfR.jpg",
    "trailerId": "MTWGd-63sIM",
    "trailerUrl": "https://www.youtube.com/embed/MTWGd-63sIM",
    "poster_image": "https://media.themoviedb.org/t/p/w355_and_h200_multi_faces/18iGjkavP8KLfyU3Ifkp9s2bSvD.jpg"
  },
  {
    "id": "1262740",
    "type": "movie",
    "title": "Baby Invasion",
    "content": "Baby Invasion available now on Apple, Amazon, and EDGLRD.COM",
    "backdrop": "https://media.themoviedb.org/t/p/w1920_and_h427_multi_faces/65MjUv58XqVWyXl4ACH6D7KHG4R.jpg",
    "trailerId": "poi718hkcYE",
    "trailerUrl": "https://www.youtube.com/embed/poi718hkcYE",
    "poster_image": "https://media.themoviedb.org/t/p/w355_and_h200_multi_faces/18iGjkavP8KLfyU3Ifkp9s2bSvD.jpg"
  },
  {
    "id": "1109255",
    "type": "movie",
    "title": "Parthenope",
    "content": "Official UK Trailer",
    "backdrop": "https://media.themoviedb.org/t/p/w1920_and_h427_multi_faces/aACb16EooaTSWGHwjsoeGe8DmyF.jpg",
    "trailerId": "AQBB13EI7vU",
    "trailerUrl": "https://www.youtube.com/embed/AQBB13EI7vU",
    "poster_image": "https://media.themoviedb.org/t/p/w355_and_h200_multi_faces/18iGjkavP8KLfyU3Ifkp9s2bSvD.jpg"
  },
  {
    "id": "972533",
    "type": "movie",
    "title": "Last Breath",
    "content": "Watch At Home Now",
    "backdrop": "https://media.themoviedb.org/t/p/w1920_and_h427_multi_faces/dGULFnPJKPh0sdu3F64YmQ0qcym.jpg",
    "trailerId": "YAlGr7FT69Y",
    "trailerUrl": "https://www.youtube.com/embed/YAlGr7FT69Y",
    "poster_image": "https://media.themoviedb.org/t/p/w355_and_h200_multi_faces/18iGjkavP8KLfyU3Ifkp9s2bSvD.jpg"
  },
  {
    "id": "1127767",
    "type": "movie",
    "title": "Riff Raff",
    "content": "Official Trailer",
    "backdrop": "https://media.themoviedb.org/t/p/w1920_and_h427_multi_faces/dAeubkAjzTCoP3VFFxu0Btm4mFp.jpg",
    "trailerId": "2UleI__TC04",
    "trailerUrl": "https://www.youtube.com/embed/2UleI__TC04",
    "poster_image": "https://media.themoviedb.org/t/p/w355_and_h200_multi_faces/18iGjkavP8KLfyU3Ifkp9s2bSvD.jpg"
  },
  {
    "id": "4348",
    "type": "movie",
    "title": "Pride & Prejudice",
    "content": "20th Anniversary Release Official Trailer",
    "backdrop": "https://media.themoviedb.org/t/p/w1920_and_h427_multi_faces/pgEWI7yGYF0mM5Uf1YxSOHsBkJR.jpg",
    "trailerId": "tbW-pmLT5UU",
    "trailerUrl": "https://www.youtube.com/embed/tbW-pmLT5UU",
    "poster_image": "https://media.themoviedb.org/t/p/w355_and_h200_multi_faces/18iGjkavP8KLfyU3Ifkp9s2bSvD.jpg"
  },
  {
    "id": "823219",
    "type": "movie",
    "title": "Flow",
    "content": "In UK Cinemas 21 March",
    "backdrop": "https://media.themoviedb.org/t/p/w1920_and_h427_multi_faces/zdy3h2sMppVp1Q41HpLiyF5w7es.jpg",
    "trailerId": "xLTJ6-8e46M",
    "trailerUrl": "https://www.youtube.com/embed/xLTJ6-8e46M",
    "poster_image": "https://media.themoviedb.org/t/p/w355_and_h200_multi_faces/18iGjkavP8KLfyU3Ifkp9s2bSvD.jpg"
  },
  {
    "id": "1280672",
    "type": "movie",
    "title": "One of Them Days",
    "content": "SZA is Alyssa",
    "backdrop": "https://media.themoviedb.org/t/p/w1920_and_h427_multi_faces/t25z4ggC2Uvs3EhI66lxVO2jDp5.jpg",
    "trailerId": "W0ZFkibrq0U",
    "trailerUrl": "https://www.youtube.com/embed/W0ZFkibrq0U",
    "poster_image": "https://media.themoviedb.org/t/p/w355_and_h200_multi_faces/18iGjkavP8KLfyU3Ifkp9s2bSvD.jpg"
  },
  {
    "id": "5968",
    "type": "movie",
    "title": "The Woman in Red",
    "content": "Official Trailer",
    "backdrop": "https://media.themoviedb.org/t/p/w1920_and_h427_multi_faces/rSeq6k5OlrDEBaa1nJSzq2J8upZ.jpg",
    "trailerId": "45ofiq9cWiY",
    "trailerUrl": "https://www.youtube.com/embed/45ofiq9cWiY",
    "poster_image": "https://media.themoviedb.org/t/p/w355_and_h200_multi_faces/18iGjkavP8KLfyU3Ifkp9s2bSvD.jpg"
  },
  {
    "id": "128",
    "type": "movie",
    "title": "Princess Mononoke",
    "content": "4K Restoration Official Trailer",
    "backdrop": "https://media.themoviedb.org/t/p/w1920_and_h427_multi_faces/gl0jzn4BupSbL2qMVeqrjKkF9Js.jpg",
    "trailerId": "I1dHzoRl0sQ",
    "trailerUrl": "https://www.youtube.com/embed/I1dHzoRl0sQ",
    "poster_image": "https://media.themoviedb.org/t/p/w355_and_h200_multi_faces/18iGjkavP8KLfyU3Ifkp9s2bSvD.jpg"
  },
  {
    "id": "1200801",
    "type": "movie",
    "title": "F Marry Kill",
    "content": "thinking about f marry kill having real consequences and suddenly i\u2019m sweating",
    "backdrop": "https://media.themoviedb.org/t/p/w1920_and_h427_multi_faces/kYC6Z4XUvZ9JQKhrkvsif4bAJl3.jpg",
    "trailerId": "C0-3pXOPzLk",
    "trailerUrl": "https://www.youtube.com/embed/C0-3pXOPzLk",
    "poster_image": "https://media.themoviedb.org/t/p/w355_and_h200_multi_faces/18iGjkavP8KLfyU3Ifkp9s2bSvD.jpg"
  },
  {
    "id": "661539",
    "type": "movie",
    "title": "A Complete Unknown",
    "content": "Hard Rain Review",
    "backdrop": "https://media.themoviedb.org/t/p/w1920_and_h427_multi_faces/d2faCjeaynI2nPDVh9PiRapcLcl.jpg",
    "trailerId": "F5E1ReqMnlo",
    "trailerUrl": "https://www.youtube.com/embed/F5E1ReqMnlo",
    "poster_image": "https://media.themoviedb.org/t/p/w355_and_h200_multi_faces/18iGjkavP8KLfyU3Ifkp9s2bSvD.jpg"
  },
  {
    "id": "402431",
    "type": "movie",
    "title": "Wicked",
    "content": "Streaming Now on Peacock",
    "backdrop": "https://media.themoviedb.org/t/p/w1920_and_h427_multi_faces/uKb22E0nlzr914bA9KyA5CVCOlV.jpg",
    "trailerId": "kOnQ1sexTuc",
    "trailerUrl": "https://www.youtube.com/embed/kOnQ1sexTuc",
    "poster_image": "https://media.themoviedb.org/t/p/w355_and_h200_multi_faces/18iGjkavP8KLfyU3Ifkp9s2bSvD.jpg"
  },
  {
    "id": "1235623",
    "type": "movie",
    "title": "Eye for an Eye 2",
    "content": "Official Trailer [Subtitled]",
    "backdrop": "https://media.themoviedb.org/t/p/w1920_and_h427_multi_faces/bx6LoGl8L3hwgOCoD2H8JgIu7uC.jpg",
    "trailerId": "FRD0KojW03E",
    "trailerUrl": "https://www.youtube.com/embed/FRD0KojW03E",
    "poster_image": "https://media.themoviedb.org/t/p/w355_and_h200_multi_faces/18iGjkavP8KLfyU3Ifkp9s2bSvD.jpg"
  },
  {
    "id": "12639",
    "type": "movie",
    "title": "Return of the Seven",
    "content": "Classic Trailer",
    "backdrop": "https://media.themoviedb.org/t/p/w1920_and_h427_multi_faces/64ABp1dJnwqZJl9DIEMe6UObhOu.jpg",
    "trailerId": "pCz94aD2JfI",
    "trailerUrl": "https://www.youtube.com/embed/pCz94aD2JfI",
    "poster_image": "https://media.themoviedb.org/t/p/w355_and_h200_multi_faces/18iGjkavP8KLfyU3Ifkp9s2bSvD.jpg"
  },
  {
    "id": "956",
    "type": "movie",
    "title": "Mission: Impossible III",
    "content": "Official Trailer",
    "backdrop": "https://media.themoviedb.org/t/p/w1920_and_h427_multi_faces/mOyF7rHVLF6uLbyb18FWTmcrjJe.jpg",
    "trailerId": "4oVva0muTE8",
    "trailerUrl": "https://www.youtube.com/embed/4oVva0muTE8",
    "poster_image": "https://media.themoviedb.org/t/p/w355_and_h200_multi_faces/18iGjkavP8KLfyU3Ifkp9s2bSvD.jpg"
  },
  {
    "id": "784524",
    "type": "movie",
    "title": "Magazine Dreams",
    "content": "Obsession",
    "backdrop": "https://media.themoviedb.org/t/p/w1920_and_h427_multi_faces/1U9VAeUj2YE6GStU3ISXDuFMBSc.jpg",
    "trailerId": "fH4PxZtOA0s",
    "trailerUrl": "https://www.youtube.com/embed/fH4PxZtOA0s",
    "poster_image": "https://media.themoviedb.org/t/p/w355_and_h200_multi_faces/18iGjkavP8KLfyU3Ifkp9s2bSvD.jpg"
  },
  {
    "id": "1225572",
    "type": "movie",
    "title": "Screamboat",
    "content": "Final Trailer",
    "backdrop": "https://media.themoviedb.org/t/p/w1920_and_h427_multi_faces/nPhej37pX5OlL8gWjg3jL06izz1.jpg",
    "trailerId": "gE3TbWfKTMs",
    "trailerUrl": "https://www.youtube.com/embed/gE3TbWfKTMs",
    "poster_image": "https://media.themoviedb.org/t/p/w355_and_h200_multi_faces/18iGjkavP8KLfyU3Ifkp9s2bSvD.jpg"
  },
  {
    "id": "1169789",
    "type": "movie",
    "title": "Bob Trevino Likes It",
    "content": "It's never too late to reach out and discover something new.",
    "backdrop": "https://media.themoviedb.org/t/p/w1920_and_h427_multi_faces/kQ7Wf46pytz7rgiafjHEFPnK5NT.jpg",
    "trailerId": "hRflTPCRdIE",
    "trailerUrl": "https://www.youtube.com/embed/hRflTPCRdIE",
    "poster_image": "https://media.themoviedb.org/t/p/w355_and_h200_multi_faces/18iGjkavP8KLfyU3Ifkp9s2bSvD.jpg"
  },
  {
    "id": "696506",
    "type": "movie",
    "title": "Mickey 17",
    "content": "Another day, another death\u2026 and another\u2026 and another.",
    "backdrop": "https://media.themoviedb.org/t/p/w1920_and_h427_multi_faces/qUc0Hol3eP74dbW4YyqT6oRLYgT.jpg",
    "trailerId": "0cOrjAsV_-g",
    "trailerUrl": "https://www.youtube.com/embed/0cOrjAsV_-g",
    "poster_image": "https://media.themoviedb.org/t/p/w355_and_h200_multi_faces/18iGjkavP8KLfyU3Ifkp9s2bSvD.jpg"
  },
  {
    "id": "1202479",
    "type": "movie",
    "title": "Opus",
    "content": "Can you handle the truth?",
    "backdrop": "https://media.themoviedb.org/t/p/w1920_and_h427_multi_faces/5zz7MfcUhYpxT6AaNyUF7jwOmKh.jpg",
    "trailerId": "rifr_qti9vg",
    "trailerUrl": "https://www.youtube.com/embed/rifr_qti9vg",
    "poster_image": "https://media.themoviedb.org/t/p/w355_and_h200_multi_faces/18iGjkavP8KLfyU3Ifkp9s2bSvD.jpg"
  },
  {
    "id": "324544",
    "type": "movie",
    "title": "In the Lost Lands",
    "content": "Prepare For Survival",
    "backdrop": "https://media.themoviedb.org/t/p/w1920_and_h427_multi_faces/eOKpbUpd178x9Z2grd3vC74kkkU.jpg",
    "trailerId": "da2PBvAqao8",
    "trailerUrl": "https://www.youtube.com/embed/da2PBvAqao8",
    "poster_image": "https://media.themoviedb.org/t/p/w355_and_h200_multi_faces/18iGjkavP8KLfyU3Ifkp9s2bSvD.jpg"
  },
  {
    "id": "1195506",
    "type": "movie",
    "title": "Novocaine",
    "content": "Thrash 30",
    "backdrop": "https://media.themoviedb.org/t/p/w1920_and_h427_multi_faces/sNx1A3822kEbqeUxvo5A08o4N7o.jpg",
    "trailerId": "nRaFFlW-OqQ",
    "trailerUrl": "https://www.youtube.com/embed/nRaFFlW-OqQ",
    "poster_image": "https://media.themoviedb.org/t/p/w355_and_h200_multi_faces/18iGjkavP8KLfyU3Ifkp9s2bSvD.jpg"
  },
  {
    "id": "1083968",
    "type": "movie",
    "title": "Locked",
    "content": "Meet William",
    "backdrop": "https://media.themoviedb.org/t/p/w1920_and_h427_multi_faces/wzROc903oP94u1vDoVT8m02fqZy.jpg",
    "trailerId": "O7O547jeGIg",
    "trailerUrl": "https://www.youtube.com/embed/O7O547jeGIg",
    "poster_image": "https://media.themoviedb.org/t/p/w355_and_h200_multi_faces/18iGjkavP8KLfyU3Ifkp9s2bSvD.jpg"
  },
  {
    "id": "870360",
    "type": "movie",
    "title": "The Day the Earth Blew Up: A Looney Tunes Movie",
    "content": "\"The Start\"",
    "backdrop": "https://media.themoviedb.org/t/p/w1920_and_h427_multi_faces/sYt5JmwlHctlfwvGtOZSjtlvv4j.jpg",
    "trailerId": "uy8rOv6fhFs",
    "trailerUrl": "https://www.youtube.com/embed/uy8rOv6fhFs",
    "poster_image": "https://media.themoviedb.org/t/p/w355_and_h200_multi_faces/18iGjkavP8KLfyU3Ifkp9s2bSvD.jpg"
  },
  {
    "id": "1437627",
    "type": "movie",
    "title": "Black Heat",
    "content": "Official Trailer",
    "backdrop": "https://media.themoviedb.org/t/p/w1920_and_h427_multi_faces",
    "trailerId": "9dnMDKk47LY",
    "trailerUrl": "https://www.youtube.com/embed/9dnMDKk47LY",
    "poster_image": "https://media.themoviedb.org/t/p/w355_and_h200_multi_faces/18iGjkavP8KLfyU3Ifkp9s2bSvD.jpg"
  },
  {
    "id": "1233575",
    "type": "movie",
    "title": "Black Bag",
    "content": "Deadly 30",
    "backdrop": "https://media.themoviedb.org/t/p/w1920_and_h427_multi_faces/gxO51FVgADhYGGnnRPIlutVqb30.jpg",
    "trailerId": "o43faZjJjYs",
    "trailerUrl": "https://www.youtube.com/embed/o43faZjJjYs",
    "poster_image": "https://media.themoviedb.org/t/p/w355_and_h200_multi_faces/18iGjkavP8KLfyU3Ifkp9s2bSvD.jpg"
  }
]